scanorama/__init__.py
scanorama/scanorama.py
scanorama/utils.py
scanorama-1.7.4.dist-info/LICENSE
scanorama-1.7.4.dist-info/METADATA
scanorama-1.7.4.dist-info/WHEEL
scanorama-1.7.4.dist-info/top_level.txt
scanorama-1.7.4.dist-info/RECORD
