Metadata-Version: 2.1
Name: scanorama
Version: 1.7.4
Summary: Panoramic stitching of heterogeneous single cell transcriptomic data
Home-page: https://github.com/brianhie/scanorama
Author: Brian Hie
Author-email: brianhie@stanford.edu
License: MIT
License-File: LICENSE
Requires-Dist: annoy >=1.11.5
Requires-Dist: fbpca >=1.0
Requires-Dist: geosketch >=1.0
Requires-Dist: intervaltree >=3.1.0
Requires-Dist: matplotlib >=2.0.2
Requires-Dist: numpy >=1.12.0
Requires-Dist: scipy >=1.0.0
Requires-Dist: scikit-learn >=0.20rc1
